warp_scheduler.v
module warp_scheduler (
    input clk,
    input reset,
    input [31:0] warp_ready,
    input [31:0] warp_stalled,
    output reg [4:0] next_warp,
    output reg warp_valid
);
    reg [4:0] current_ptr;
    wire [31:0] warp_eligible;

    assign warp_eligible = warp_ready & ~warp_stalled;

    integer i;
    reg [4:0] selected;
    reg found;

    always @(posedge clk or posedge reset) begin
        if (reset) begin
            current_ptr <= 0;
            next_warp <= 0;
            warp_valid <= 0;
        end else begin
            found = 0;
            selected = 0;
            warp_valid = 0;

            for (i = 0; i < 32; i = i + 1) begin
                if (!found && warp_eligible[(current_ptr + i) % 32]) begin
                    selected = (current_ptr + i) % 32;
                    found = 1;
                end
            end

            if (found) begin
                next_warp <= selected;
                warp_valid <= 1;
                current_ptr <= (selected + 1) % 32;
            end
        end
    end
endmodule

tb_warp_scheduler.v
module tb_warp_scheduler();
    reg clk;
    reg reset;
    reg [31:0] warp_ready;
    reg [31:0] warp_stalled;
    wire [4:0] next_warp;
    wire warp_valid;
    integer count;

    warp_scheduler dut (
        .clk(clk),
        .reset(reset),
        .warp_ready(warp_ready),
        .warp_stalled(warp_stalled),
        .next_warp(next_warp),
        .warp_valid(warp_valid)
    );

    // Clock generation
    initial begin
        clk = 0;
        forever #5 clk = ~clk;
    end

    // Test process
    initial begin
        $dumpfile("waves.vcd");
        $dumpvars(0, tb_warp_scheduler);

        reset = 1;
        warp_ready = 0;
        warp_stalled = 0;
        #20;
        reset = 0;

        // Test 1
        $display("\n=== Test 1: Single Warp ===");
        warp_ready = 32'b00000000000000000000000000000001;
        #10;
        wait (warp_valid == 1);
        $display("[%0t] Warp %0d selected", $time, next_warp);

        // Test 2
        $display("\n=== Test 2: Two Warps ===");
        warp_ready = 32'b00000000000000000000000000000011;
        #10;

        for (count = 0; count < 4; count = count + 1) begin
            wait (warp_valid == 1);
            $display("[%0t] Warp %0d selected", $time, next_warp);
            #10;
        end

        $display("\n=== All tests passed! ===");
        $finish;
    end
endmodule

waves.vcd
$date
	Sun Apr 20 10:44:15 2025
$end
$version
	Icarus Verilog
$end
$timescale
	1s
$end
$scope module tb_warp_scheduler $end
$var wire 1 ! warp_valid $end
$var wire 5 " next_warp [4:0] $end
$var reg 1 # clk $end
$var reg 1 $ reset $end
$var reg 32 % warp_ready [31:0] $end
$var reg 32 & warp_stalled [31:0] $end
$var integer 32 ' count [31:0] $end
$scope module dut $end
$var wire 1 # clk $end
$var wire 1 $ reset $end
$var wire 32 ( warp_eligible [31:0] $end
$var wire 32 ) warp_ready [31:0] $end
$var wire 32 * warp_stalled [31:0] $end
$var reg 5 + current_ptr [4:0] $end
$var reg 1 , found $end
$var reg 5 - next_warp [4:0] $end
$var reg 5 . selected [4:0] $end
$var reg 1 ! warp_valid $end
$var integer 32 / i [31:0] $end
$upscope $end
$upscope $end
$enddefinitions $end
#0
$dumpvars
bx /
bx .
b0 -
x,
b0 +
b0 *
b0 )
b0 (
bx '
b0 &
b0 %
1$
0#
b0 "
0!
$end
#5
1#
#10
0#
#15
1#
#20
b1 (
0#
b1 %
b1 )
0$
#25
b1 +
1!
b100000 /
b0 .
1,
1#
#30
b11 (
0#
b11 %
b11 )
#35
b10 +
b1 "
b1 -
b1 .
b100000 /
1!
1,
1#
#40
0#
b0 '
#45
b1 +
b0 "
b0 -
b100000 /
1!
b0 .
1,
1#
#50
0#
b1 '
#55
b10 +
b1 "
b1 -
b1 .
b100000 /
1!
1,
1#
#60
0#
b10 '
#65
b1 +
b0 "
b0 -
b100000 /
1!
b0 .
1,
1#
#70
0#
b11 '
#75
b10 +
b1 "
b1 -
b1 .
b100000 /
1!
1,
1#
#80
0#
b100 '
